README.md
setup.py
arnger/__init__.py
arnger/locator.py
arnger1.egg-info/PKG-INFO
arnger1.egg-info/SOURCES.txt
arnger1.egg-info/dependency_links.txt
arnger1.egg-info/requires.txt
arnger1.egg-info/top_level.txt